.DS_Store
dimsim/__init__.py
dimsim/dimsim.py
dimsim/pinyin_to_simplified.pickle
dimsim/pinyin_to_traditional.pickle
chinesesoundex_1.0-1.0.dist-info/LICENSE
chinesesoundex_1.0-1.0.dist-info/METADATA
chinesesoundex_1.0-1.0.dist-info/WHEEL
chinesesoundex_1.0-1.0.dist-info/top_level.txt
chinesesoundex_1.0-1.0.dist-info/RECORD
